ptyrad/__init__.py
ptyrad/__main__.py
ptyrad/cli.py
ptyrad/constraints.py
ptyrad/forward.py
ptyrad/initialization.py
ptyrad/load.py
ptyrad/losses.py
ptyrad/models.py
ptyrad/reconstruction.py
ptyrad/save.py
ptyrad/visualization.py
ptyrad/params/__init__.py
ptyrad/params/base.py
ptyrad/params/constraint_params.py
ptyrad/params/hypertune_params.py
ptyrad/params/init_params.py
ptyrad/params/loss_params.py
ptyrad/params/model_params.py
ptyrad/params/recon_params.py
ptyrad/utils/__init__.py
ptyrad/utils/common.py
ptyrad/utils/dev_tools.py
ptyrad/utils/image_proc.py
ptyrad/utils/math_ops.py
ptyrad/utils/physics.py
ptyrad-0.1.0b12.dist-info/licenses/LICENSE
ptyrad-0.1.0b12.dist-info/METADATA
ptyrad-0.1.0b12.dist-info/WHEEL
ptyrad-0.1.0b12.dist-info/entry_points.txt
ptyrad-0.1.0b12.dist-info/top_level.txt
ptyrad-0.1.0b12.dist-info/RECORD
