Metadata-Version: 2.4
Name: ptyrad
Version: 0.1.0b12
Summary: PtyRAD: Ptychographic Reconstruction with Automatic Differentiation
Author-email: Chia-Hao Lee <cl2696@cornell.edu>
License-Expression: LGPL-3.0
Project-URL: Homepage, https://github.com/chiahao3/ptyrad
Project-URL: Repository, https://github.com/chiahao3/ptyrad
Project-URL: Issues, https://github.com/chiahao3/ptyrad/issues
Project-URL: Changelog, https://github.com/chiahao3/ptyrad/blob/main/CHANGELOG.md
Keywords: Ptychography
Classifier: Development Status :: 4 - Beta
Classifier: Programming Language :: Python :: 3
Classifier: Operating System :: OS Independent
Requires-Python: >=3.10
License-File: LICENSE
Requires-Dist: accelerate
Requires-Dist: h5py
Requires-Dist: jupyter
Requires-Dist: matplotlib
Requires-Dist: optuna
Requires-Dist: pydantic
Requires-Dist: scikit-learn
Requires-Dist: scipy
Requires-Dist: tifffile
Requires-Dist: torch>=2.0
Requires-Dist: torchvision
Dynamic: license-file
